MANIFEST.in
README.md
setup.py
ca_toolkit/__init__.py
ca_toolkit.egg-info/PKG-INFO
ca_toolkit.egg-info/SOURCES.txt
ca_toolkit.egg-info/dependency_links.txt
ca_toolkit.egg-info/requires.txt
ca_toolkit.egg-info/top_level.txt
src/evolve.c
src/evolve.h
src/mod_evolve.c