Metadata-Version: 1.0
Name: ca-toolkit
Version: 0.1
Summary: Python toolkit for Cellular Automata
Home-page: https://github.com/archman/ca-toolkit.git
Author: Tong Zhang
Author-email: warriorlance@gmail.com
License: UNKNOWN
Platform: UNKNOWN
